Metadata-Version: 2.1
Name: example_package_mclaughlinliam3
Version: 0.0.1
Summary: A small example package
Author-email: Liam McLaughlin <boom2449@gmail.com>
Project-URL: Homepage, https://github.com/pypa/sampleproject
Project-URL: Issues, https://github.com/pypa/sampleproject/issues
Classifier: Programming Language :: Python :: 3
Classifier: License :: OSI Approved :: MIT License
Classifier: Operating System :: OS Independent
Requires-Python: >=3.8
License-File: LICENSE
Requires-Dist: numpy
Provides-Extra: net
Requires-Dist: networkx ; extra == 'net'
